abxr/apk.py
abxr/configuration_package.py
abxr/device.py
abxr/device_commands.py
abxr/display.py
abxr/font5x8.bin
abxr/provision.py
abxr/setup_mode.py
abxr/version.py
abxrfpt-0.6.0.dist-info/licenses/LICENSE
abxrfpt-0.6.0.dist-info/METADATA
abxrfpt-0.6.0.dist-info/WHEEL
abxrfpt-0.6.0.dist-info/entry_points.txt
abxrfpt-0.6.0.dist-info/top_level.txt
abxrfpt-0.6.0.dist-info/RECORD
