Metadata-Version: 2.4
Name: abxrfpt
Version: 0.6.0
Summary: ArborXR Field Provisioning Tools
Author-email: Peter Peterson <peter@arborxr.com>
License-File: LICENSE
Requires-Dist: androguard
Requires-Dist: pyudev
Requires-Dist: adafruit-circuitpython-ssd1306
Requires-Dist: setuptools
Dynamic: license-file
